console.py
dep/__init__.py
dep/click.py
dep/commands.py
dep/config.py
dep/dependency.py
dep/formatters.py
dep/outputters.py
dep/values.py
delineate_io-0.0.18.dist-info/LICENSE
delineate_io-0.0.18.dist-info/METADATA
delineate_io-0.0.18.dist-info/WHEEL
delineate_io-0.0.18.dist-info/entry_points.txt
delineate_io-0.0.18.dist-info/top_level.txt
delineate_io-0.0.18.dist-info/RECORD
