Metadata-Version: 2.1
Name: delineate-io
Version: 0.0.18
Summary: Tools to simplify the management of local environments
Home-page: https://github.com/delineateio/delineateio.tools
Author: https://www.delineate.io
Author-email: oss@delineate.io
License: MIT
Download-URL: https://github.com/delineateio/delineateio.tools/tarball/0.0.18
Platform: UNKNOWN
Classifier: Programming Language :: Python :: 3
Classifier: License :: OSI Approved :: MIT License
Classifier: Operating System :: OS Independent
Requires-Dist: click (==7.0)
Requires-Dist: PrettyTable (==0.7.2)
Requires-Dist: termcolor (==1.1.0)
